webuild/__init__.py
webuild/admin.py
webuild/apps.py
webuild/forms.py
webuild/models.py
webuild/tests.py
webuild/urls.py
webuild/views.py
webuild/static/webuild/css/style.css
webuild/static/webuild/img/apple-touch-icon.png
webuild/static/webuild/img/favicon.png
webuild/static/webuild/img/hero-bg.jpg
webuild/static/webuild/js/jquery-3.6.0.min.js
webuild/static/webuild/js/jquery.cookie.js
webuild/static/webuild/js/main.js
webuild/static/webuild/scss/_footer.scss
webuild/static/webuild/scss/_general.scss
webuild/static/webuild/scss/_header.scss
webuild/static/webuild/scss/_hero.scss
webuild/static/webuild/scss/_sections.scss
webuild/static/webuild/scss/_variables.scss
webuild/static/webuild/scss/style.scss
webuild/static/webuild/vendor/bootstrap/css/bootstrap-grid.css
webuild/static/webuild/vendor/bootstrap/css/bootstrap-grid.css.map
webuild/static/webuild/vendor/bootstrap/css/bootstrap-grid.min.css
webuild/static/webuild/vendor/bootstrap/css/bootstrap-grid.min.css.map
webuild/static/webuild/vendor/bootstrap/css/bootstrap-grid.rtl.css
webuild/static/webuild/vendor/bootstrap/css/bootstrap-grid.rtl.css.map
webuild/static/webuild/vendor/bootstrap/css/bootstrap-grid.rtl.min.css
webuild/static/webuild/vendor/bootstrap/css/bootstrap-grid.rtl.min.css.map
webuild/static/webuild/vendor/bootstrap/css/bootstrap-reboot.css
webuild/static/webuild/vendor/bootstrap/css/bootstrap-reboot.css.map
webuild/static/webuild/vendor/bootstrap/css/bootstrap-reboot.min.css
webuild/static/webuild/vendor/bootstrap/css/bootstrap-reboot.min.css.map
webuild/static/webuild/vendor/bootstrap/css/bootstrap-reboot.rtl.css
webuild/static/webuild/vendor/bootstrap/css/bootstrap-reboot.rtl.css.map
webuild/static/webuild/vendor/bootstrap/css/bootstrap-reboot.rtl.min.css
webuild/static/webuild/vendor/bootstrap/css/bootstrap-reboot.rtl.min.css.map
webuild/static/webuild/vendor/bootstrap/css/bootstrap-utilities.css
webuild/static/webuild/vendor/bootstrap/css/bootstrap-utilities.css.map
django_webuild_ds-0.0.2.dist-info/LICENSE
django_webuild_ds-0.0.2.dist-info/METADATA
django_webuild_ds-0.0.2.dist-info/WHEEL
django_webuild_ds-0.0.2.dist-info/top_level.txt
django_webuild_ds-0.0.2.dist-info/RECORD
